[
  {
    "EN" : 1,
    "SN" : 8,
    "Title" : "Starling City",
    "Date" : "Oct 15th, 2019",
    "Still" : "\/2CvyZm8rnkcTyAYxxsZlJfrl4gw.jpg"
  },
  {
    "EN" : 2,
    "SN" : 8,
    "Title" : "Welcome To Hong Kong",
    "Date" : "Oct 22nd, 2019",
    "Still" : "\/skUsPwXvwgeUM6GWST4jvMQksYt.jpg"
  },
  {
    "EN" : 3,
    "SN" : 8,
    "Title" : "Leap of Faith",
    "Date" : "Oct 29th, 2019",
    "Still" : "\/5bx7Yso1vtF8pw1b2GTlGGlOU7O.jpg"
  },
  {
    "EN" : 4,
    "SN" : 8,
    "Title" : "Present Tense",
    "Date" : "Nov 5th, 2019",
    "Still" : "\/rUzFOgPQAeSgP595sMV16um07cT.jpg"
  },
  {
    "EN" : 5,
    "SN" : 8,
    "Title" : "Prochnost",
    "Date" : "Nov 19th, 2019",
    "Still" : "\/p4a65rbBGkyBtntLR14NDPoAQ5G.jpg"
  },
  {
    "EN" : 6,
    "SN" : 8,
    "Title" : "Reset",
    "Date" : "Nov 26th, 2019",
    "Still" : "\/crOv7aIpdZA7YW6iyRBR9nAiEUr.jpg"
  },
  {
    "EN" : 7,
    "SN" : 8,
    "Title" : "Purgatory",
    "Date" : "Dec 3rd, 2019",
    "Still" : "\/lKkwtnAdMRn6i6oh6lscLNNtLww.jpg"
  },
  {
    "EN" : 8,
    "SN" : 8,
    "Title" : "Crisis on Infinite Earths: Part Four (IV)",
    "Date" : "Jan 14th, 2020",
    "Still" : "\/sNeXDfwMeE0s82aGGxo34A12H3Y.jpg"
  },
  {
    "EN" : 9,
    "SN" : 8,
    "Title" : "Green Arrow & The Canaries",
    "Date" : "Jan 21st, 2020",
    "Still" : "\/z5XMKTLtnqCVl4RhWy5DyYMq4yk.jpg"
  },
  {
    "EN" : 10,
    "SN" : 8,
    "Title" : "Fadeout",
    "Date" : "Jan 28th, 2020",
    "Still" : "\/x2uJkULqhVhosfjlqTknZtv1QyZ.jpg"
  },
  {
    "EN" : 1,
    "SN" : 7,
    "Title" : "Inmate 4587",
    "Date" : "Oct 15th, 2018",
    "Still" : "\/3gxR1QYAmNIm0iZmHjutjOP6rDf.jpg"
  },
  {
    "EN" : 2,
    "SN" : 7,
    "Title" : "The Longbow Hunters",
    "Date" : "Oct 22nd, 2018",
    "Still" : "\/biLXpyTnmGji9yrVMs1Cert3UgE.jpg"
  },
  {
    "EN" : 3,
    "SN" : 7,
    "Title" : "Crossing Lines",
    "Date" : "Oct 29th, 2018",
    "Still" : "\/8PBuj1eviwJ14y5TDdELhY9KazK.jpg"
  },
  {
    "EN" : 4,
    "SN" : 7,
    "Title" : "Level Two",
    "Date" : "Nov 5th, 2018",
    "Still" : "\/tkXPizvNSYcktOE81df44SwVQf5.jpg"
  },
  {
    "EN" : 5,
    "SN" : 7,
    "Title" : "The Demon",
    "Date" : "Nov 12th, 2018",
    "Still" : "\/6FEFqcj0wdtrhZ6JkuLqK1jvei6.jpg"
  },
  {
    "EN" : 6,
    "SN" : 7,
    "Title" : "Due Process",
    "Date" : "Nov 19th, 2018",
    "Still" : "\/unzLWewv3aEiKCqtBkxOD7dTKwv.jpg"
  },
  {
    "EN" : 7,
    "SN" : 7,
    "Title" : "The Slabside Redemption",
    "Date" : "Nov 26th, 2018",
    "Still" : "\/p4PlQkRxIvRvefPqMumtYr6BLHP.jpg"
  },
  {
    "EN" : 8,
    "SN" : 7,
    "Title" : "Unmasked",
    "Date" : "Dec 3rd, 2018",
    "Still" : "\/szvvC604eJv8wj3Lg1SmKU9WIvW.jpg"
  },
  {
    "EN" : 9,
    "SN" : 7,
    "Title" : "Elseworlds (II)",
    "Date" : "Dec 10th, 2018",
    "Still" : "\/z6oJIMX7uZaXn2rSg5YMp9sD4IH.jpg"
  },
  {
    "EN" : 10,
    "SN" : 7,
    "Title" : "My Name Is Emiko Queen",
    "Date" : "Jan 21st, 2019",
    "Still" : "\/2mWmzJdqfnYLf6BMQXGVnYHCI6f.jpg"
  },
  {
    "EN" : 11,
    "SN" : 7,
    "Title" : "Past Sins",
    "Date" : "Jan 28th, 2019",
    "Still" : "\/z4HjkRe5gJIZ9nOhZilnbeOFvYJ.jpg"
  },
  {
    "EN" : 12,
    "SN" : 7,
    "Title" : "Emerald Archer",
    "Date" : "Feb 4th, 2019",
    "Still" : "\/hlqzGOIzGPCQDTFw1szuTBUO9Mg.jpg"
  },
  {
    "EN" : 13,
    "SN" : 7,
    "Title" : "Star City Slayer",
    "Date" : "Feb 11th, 2019",
    "Still" : "\/oDTIQrnYtkQLH3EPEZ6XETcIEzZ.jpg"
  },
  {
    "EN" : 14,
    "SN" : 7,
    "Title" : "Brothers & Sisters",
    "Date" : "Mar 4th, 2019",
    "Still" : "\/v44k9w80CxYTzRACGFjjK3ZCmY6.jpg"
  },
  {
    "EN" : 15,
    "SN" : 7,
    "Title" : "Training Day",
    "Date" : "Mar 11th, 2019",
    "Still" : "\/5ZGMcPQhTjHiKLtKcBSyUErkw2k.jpg"
  },
  {
    "EN" : 16,
    "SN" : 7,
    "Title" : "Star City 2040",
    "Date" : "Mar 18th, 2019",
    "Still" : "\/iPIvzRcGlhRG0SqQlhDPXc0FMPC.jpg"
  },
  {
    "EN" : 17,
    "SN" : 7,
    "Title" : "Inheritance",
    "Date" : "Mar 25th, 2019",
    "Still" : "\/8kJmuRmpieBX03YL70BFWPZBlhp.jpg"
  },
  {
    "EN" : 18,
    "SN" : 7,
    "Title" : "Lost Canary",
    "Date" : "Apr 15th, 2019",
    "Still" : "\/dRCDMIGk5tw60Nlv9brAyCAbrRf.jpg"
  },
  {
    "EN" : 19,
    "SN" : 7,
    "Title" : "Spartan",
    "Date" : "Apr 22nd, 2019",
    "Still" : "\/y4i2HOSUCxNb5qsXycA7F3JkwWz.jpg"
  },
  {
    "EN" : 20,
    "SN" : 7,
    "Title" : "Confessions",
    "Date" : "Apr 29th, 2019",
    "Still" : "\/xU1h5YDDhCXvQpfTxnDUN89ihEa.jpg"
  },
  {
    "EN" : 21,
    "SN" : 7,
    "Title" : "Living Proof",
    "Date" : "May 6th, 2019",
    "Still" : "\/pjE69p8ysl1tNQcNxanV0TPC0Tw.jpg"
  },
  {
    "EN" : 22,
    "SN" : 7,
    "Title" : "You Have Saved This City",
    "Date" : "May 13th, 2019",
    "Still" : "\/kH3EyD1IibKqyB3MGiIzyAIpdyg.jpg"
  },
  {
    "EN" : 1,
    "SN" : 6,
    "Title" : "Fallout",
    "Date" : "Oct 12th, 2017",
    "Still" : "\/tku04rIOjFHIwdkjeSGi6DQiOQp.jpg"
  },
  {
    "EN" : 2,
    "SN" : 6,
    "Title" : "Tribute",
    "Date" : "Oct 19th, 2017",
    "Still" : "\/eGwGlULe1PLqEtJf2yllWhVVrhv.jpg"
  },
  {
    "EN" : 3,
    "SN" : 6,
    "Title" : "Next of Kin",
    "Date" : "Oct 26th, 2017",
    "Still" : "\/oSpZyzjBqKPdIpbPAbYLyd7dSDv.jpg"
  },
  {
    "EN" : 4,
    "SN" : 6,
    "Title" : "Reversal",
    "Date" : "Nov 2nd, 2017",
    "Still" : "\/4vZfTCKJiCAMLIMduyVhMcZ9WdT.jpg"
  },
  {
    "EN" : 5,
    "SN" : 6,
    "Title" : "Deathstroke Returns",
    "Date" : "Nov 9th, 2017",
    "Still" : "\/iKpNoDp4onqXa0PtiA6jrBhT1Sv.jpg"
  },
  {
    "EN" : 6,
    "SN" : 6,
    "Title" : "Promises Kept",
    "Date" : "Nov 16th, 2017",
    "Still" : "\/6fGdUj9jrxeUJAu6y9wZRb98Nb0.jpg"
  },
  {
    "EN" : 7,
    "SN" : 6,
    "Title" : "Thanksgiving",
    "Date" : "Nov 23rd, 2017",
    "Still" : "\/adarSKMQhzSmupOpMlEx0P54pu4.jpg"
  },
  {
    "EN" : 8,
    "SN" : 6,
    "Title" : "Crisis on Earth-X (II)",
    "Date" : "Nov 27th, 2017",
    "Still" : "\/8uBnSngtwBE5MaMweQOf32h6sOl.jpg"
  },
  {
    "EN" : 9,
    "SN" : 6,
    "Title" : "Irreconcilable Differences",
    "Date" : "Dec 7th, 2017",
    "Still" : "\/674MdRWyRSEYkzzKuY7K0m92cAd.jpg"
  },
  {
    "EN" : 10,
    "SN" : 6,
    "Title" : "Divided",
    "Date" : "Jan 18th, 2018",
    "Still" : "\/4SzRLUqe0sVkxMwVPXtu4q7sYo3.jpg"
  },
  {
    "EN" : 11,
    "SN" : 6,
    "Title" : "We Fall",
    "Date" : "Jan 25th, 2018",
    "Still" : "\/ez3yUFmi2EtjH9ZPugyUnB1WGO4.jpg"
  },
  {
    "EN" : 12,
    "SN" : 6,
    "Title" : "All for Nothing",
    "Date" : "Feb 1st, 2018",
    "Still" : "\/cd5CjXF1Xd7zCaN7493VvUGn1s4.jpg"
  },
  {
    "EN" : 13,
    "SN" : 6,
    "Title" : "The Devil's Greatest Trick",
    "Date" : "Feb 8th, 2018",
    "Still" : "\/ajU4z8pP9oCPx0HIaEwRnPj22E7.jpg"
  },
  {
    "EN" : 14,
    "SN" : 6,
    "Title" : "Collision Course",
    "Date" : "Mar 1st, 2018",
    "Still" : "\/3qxzSeID32pkNzd4liVvWxOUpdS.jpg"
  },
  {
    "EN" : 15,
    "SN" : 6,
    "Title" : "Doppelganger",
    "Date" : "Mar 8th, 2018",
    "Still" : "\/FyxBXoa2ZwpuNN94pAU25gZ6vN.jpg"
  },
  {
    "EN" : 16,
    "SN" : 6,
    "Title" : "The Thanatos Guild",
    "Date" : "Mar 29th, 2018",
    "Still" : "\/v7sBGkfvxylH1aP5ZEsPGd0XTJw.jpg"
  },
  {
    "EN" : 17,
    "SN" : 6,
    "Title" : "Brothers in Arms",
    "Date" : "Apr 5th, 2018",
    "Still" : "\/e24WMrUA1H8Uutj2ipo0CZdWpZ1.jpg"
  },
  {
    "EN" : 18,
    "SN" : 6,
    "Title" : "Fundamentals",
    "Date" : "Apr 12th, 2018",
    "Still" : "\/aBfCd3WaEPKUL5G3hWTuNjQijoU.jpg"
  },
  {
    "EN" : 19,
    "SN" : 6,
    "Title" : "The Dragon",
    "Date" : "Apr 19th, 2018",
    "Still" : "\/bDe17biudys90VpMvYxdv1cLlSM.jpg"
  },
  {
    "EN" : 20,
    "SN" : 6,
    "Title" : "Shifting Allegiances",
    "Date" : "Apr 26th, 2018",
    "Still" : "\/qTFEkwjqJj3ejLcT9OlrknoFI1s.jpg"
  },
  {
    "EN" : 21,
    "SN" : 6,
    "Title" : "Docket No. 11-19-41-73",
    "Date" : "May 3rd, 2018",
    "Still" : "\/31FdFHr4eritXAAREyi5QcqEbon.jpg"
  },
  {
    "EN" : 22,
    "SN" : 6,
    "Title" : "The Ties That Bind",
    "Date" : "May 10th, 2018",
    "Still" : "\/e4WB4PCgA5N57avMupNLHEyaVPI.jpg"
  },
  {
    "EN" : 23,
    "SN" : 6,
    "Title" : "Life Sentence",
    "Date" : "May 17th, 2018",
    "Still" : "\/cknHTRfyBpPFwiZtytY5xbDxONu.jpg"
  },
  {
    "EN" : 1,
    "SN" : 5,
    "Title" : "Legacy",
    "Date" : "Oct 5th, 2016",
    "Still" : "\/uJmQsMSHKJiNuTSpYpJRWtRssCK.jpg"
  },
  {
    "EN" : 2,
    "SN" : 5,
    "Title" : "The Recruits",
    "Date" : "Oct 12th, 2016",
    "Still" : "\/FwIJiupVE8PEffNjjEzMJfYLpo.jpg"
  },
  {
    "EN" : 3,
    "SN" : 5,
    "Title" : "A Matter of Trust",
    "Date" : "Oct 19th, 2016",
    "Still" : "\/AuhEfrU3I7zCcMb9arnBPsN7h4h.jpg"
  },
  {
    "EN" : 4,
    "SN" : 5,
    "Title" : "Penance",
    "Date" : "Oct 26th, 2016",
    "Still" : "\/9Iq4p2MYVwA8DdEzWNdhtVm9ktX.jpg"
  },
  {
    "EN" : 5,
    "SN" : 5,
    "Title" : "Human Target",
    "Date" : "Nov 2nd, 2016",
    "Still" : "\/hQqNO7WpQpgr0ovEXb8aDg8i3Ab.jpg"
  },
  {
    "EN" : 6,
    "SN" : 5,
    "Title" : "So It Begins",
    "Date" : "Nov 9th, 2016",
    "Still" : "\/mrlg1ubymy0SJHHbkegqM330Hre.jpg"
  },
  {
    "EN" : 7,
    "SN" : 5,
    "Title" : "Vigilante",
    "Date" : "Nov 16th, 2016",
    "Still" : "\/4DEg0SWCsu0wS72OL4BX7lKmYeo.jpg"
  },
  {
    "EN" : 8,
    "SN" : 5,
    "Title" : "Invasion! (III)",
    "Date" : "Nov 30th, 2016",
    "Still" : "\/jKLvEq99daTLF6is02b7bFxmS3B.jpg"
  },
  {
    "EN" : 9,
    "SN" : 5,
    "Title" : "What We Leave Behind",
    "Date" : "Dec 7th, 2016",
    "Still" : "\/d47U5EEg6B9G4WglRHPUNW5CMwz.jpg"
  },
  {
    "EN" : 10,
    "SN" : 5,
    "Title" : "Who Are You?",
    "Date" : "Jan 25th, 2017",
    "Still" : "\/zy3NwKnTfmXdwgs9WqiYDE9sSYX.jpg"
  },
  {
    "EN" : 11,
    "SN" : 5,
    "Title" : "Second Chances",
    "Date" : "Feb 1st, 2017",
    "Still" : "\/yIPNGfOOVVQVOEeHSakhm1DI0fN.jpg"
  },
  {
    "EN" : 12,
    "SN" : 5,
    "Title" : "Bratva",
    "Date" : "Feb 8th, 2017",
    "Still" : "\/1zOf7TzIIZhOZseyLtNDroanDVZ.jpg"
  },
  {
    "EN" : 13,
    "SN" : 5,
    "Title" : "Spectre of the Gun",
    "Date" : "Feb 15th, 2017",
    "Still" : "\/zYSQ8TLS7kjPlXZ3jXMmHlL18JU.jpg"
  },
  {
    "EN" : 14,
    "SN" : 5,
    "Title" : "The Sin-Eater",
    "Date" : "Feb 22nd, 2017",
    "Still" : "\/tH7XBOwuEjB7mj7SqxtxEKj99Ov.jpg"
  },
  {
    "EN" : 15,
    "SN" : 5,
    "Title" : "Fighting Fire with Fire",
    "Date" : "Mar 1st, 2017",
    "Still" : "\/wTLSWi9EYFtBUatV31lzqtdc0nL.jpg"
  },
  {
    "EN" : 16,
    "SN" : 5,
    "Title" : "Checkmate",
    "Date" : "Mar 15th, 2017",
    "Still" : "\/mj9661jaFhqrjpTkdXrARlVx6DE.jpg"
  },
  {
    "EN" : 17,
    "SN" : 5,
    "Title" : "Kapiushon",
    "Date" : "Mar 22nd, 2017",
    "Still" : "\/bBxSGVY50HFL6LT4x5d7dfEOpH5.jpg"
  },
  {
    "EN" : 18,
    "SN" : 5,
    "Title" : "Disbanded",
    "Date" : "Mar 29th, 2017",
    "Still" : "\/hND92lNzMQ7KtShpoNHhhm2Chq3.jpg"
  },
  {
    "EN" : 19,
    "SN" : 5,
    "Title" : "Dangerous Liaisons",
    "Date" : "Apr 26th, 2017",
    "Still" : "\/8kgbz2PstsjzX5nLJty0Y6GJrnc.jpg"
  },
  {
    "EN" : 20,
    "SN" : 5,
    "Title" : "Underneath",
    "Date" : "May 3rd, 2017",
    "Still" : "\/xD9bWz3IrgzB883zxdSD7KPo8zj.jpg"
  },
  {
    "EN" : 21,
    "SN" : 5,
    "Title" : "Honor Thy Fathers",
    "Date" : "May 10th, 2017",
    "Still" : "\/euQliOnoOwleq5pHSDyUqXmG8iK.jpg"
  },
  {
    "EN" : 22,
    "SN" : 5,
    "Title" : "Missing",
    "Date" : "May 17th, 2017",
    "Still" : "\/dkxVb0DumloXzWUYFsNCSHWfL2W.jpg"
  },
  {
    "EN" : 23,
    "SN" : 5,
    "Title" : "Lian Yu",
    "Date" : "May 24th, 2017",
    "Still" : "\/apGODUKLMgUVz7e1tEUHUkybCTd.jpg"
  },
  {
    "EN" : 1,
    "SN" : 4,
    "Title" : "Green Arrow",
    "Date" : "Oct 7th, 2015",
    "Still" : "\/rlpyW1mzbQ39Op33W71yHZzarY2.jpg"
  },
  {
    "EN" : 2,
    "SN" : 4,
    "Title" : "The Candidate",
    "Date" : "Oct 14th, 2015",
    "Still" : "\/tcXQv1gommrDBU36kakR1oqXbM4.jpg"
  },
  {
    "EN" : 3,
    "SN" : 4,
    "Title" : "Restoration",
    "Date" : "Oct 21st, 2015",
    "Still" : "\/lcSKkVgYRjwM0NoNAbomUmKjFWH.jpg"
  },
  {
    "EN" : 4,
    "SN" : 4,
    "Title" : "Beyond Redemption",
    "Date" : "Oct 28th, 2015",
    "Still" : "\/uigX7F4cF5pa33fDsAej29ktj75.jpg"
  },
  {
    "EN" : 5,
    "SN" : 4,
    "Title" : "Haunted",
    "Date" : "Nov 4th, 2015",
    "Still" : "\/3nV76wPOkEYWV36Tv4K2DzE8Fz4.jpg"
  },
  {
    "EN" : 6,
    "SN" : 4,
    "Title" : "Lost Souls",
    "Date" : "Nov 11th, 2015",
    "Still" : "\/tSM2Pgv91TvLP9fmpT1JYMF9ZnT.jpg"
  },
  {
    "EN" : 7,
    "SN" : 4,
    "Title" : "Brotherhood",
    "Date" : "Nov 18th, 2015",
    "Still" : "\/vb3HqOxRgYlU5JSTh95qOmPlpP3.jpg"
  },
  {
    "EN" : 8,
    "SN" : 4,
    "Title" : "Legends of Yesterday (II)",
    "Date" : "Dec 2nd, 2015",
    "Still" : "\/DA2JOZTXRXZ4nynk6VbVaYQz8Q.jpg"
  },
  {
    "EN" : 9,
    "SN" : 4,
    "Title" : "Dark Waters",
    "Date" : "Dec 9th, 2015",
    "Still" : "\/z7jouWlGw3eh5VXBMuhBf0zOjWx.jpg"
  },
  {
    "EN" : 10,
    "SN" : 4,
    "Title" : "Blood Debts",
    "Date" : "Jan 20th, 2016",
    "Still" : "\/6lNWk79keAxAme0f1avdQb4aI9g.jpg"
  },
  {
    "EN" : 11,
    "SN" : 4,
    "Title" : "A.W.O.L.",
    "Date" : "Jan 27th, 2016",
    "Still" : "\/4CjzRxGPyfT1sXKnqEZ7S69qmtA.jpg"
  },
  {
    "EN" : 12,
    "SN" : 4,
    "Title" : "Unchained",
    "Date" : "Feb 3rd, 2016",
    "Still" : "\/cDyczgVVa7fSv8GjV53MOgoEQeE.jpg"
  },
  {
    "EN" : 13,
    "SN" : 4,
    "Title" : "Sins of the Father",
    "Date" : "Feb 10th, 2016",
    "Still" : "\/lgrjAzeBBjhTNYTkIeAhX3GV0bk.jpg"
  },
  {
    "EN" : 14,
    "SN" : 4,
    "Title" : "Code of Silence",
    "Date" : "Feb 17th, 2016",
    "Still" : "\/8eR2a3mHsjAQRLa7VkTk3Pp1f75.jpg"
  },
  {
    "EN" : 15,
    "SN" : 4,
    "Title" : "Taken",
    "Date" : "Feb 24th, 2016",
    "Still" : "\/93wwlQxF8NEAKe3zuqZlwucMh4.jpg"
  },
  {
    "EN" : 16,
    "SN" : 4,
    "Title" : "Broken Hearts",
    "Date" : "Mar 23rd, 2016",
    "Still" : "\/f3Ahdnbbzo0CdDG9E8JUrVnb0L.jpg"
  },
  {
    "EN" : 17,
    "SN" : 4,
    "Title" : "Beacon of Hope",
    "Date" : "Mar 30th, 2016",
    "Still" : "\/paXDlhdhM3smQmSpS4LqQmJNvmx.jpg"
  },
  {
    "EN" : 18,
    "SN" : 4,
    "Title" : "Eleven-Fifty-Nine",
    "Date" : "Apr 6th, 2016",
    "Still" : "\/huMoIkKlh4JIWygShWqYRndXBDz.jpg"
  },
  {
    "EN" : 19,
    "SN" : 4,
    "Title" : "Canary Cry",
    "Date" : "Apr 27th, 2016",
    "Still" : "\/pPnWESBKfNzO4xVyIgHxVk7M7yp.jpg"
  },
  {
    "EN" : 20,
    "SN" : 4,
    "Title" : "Genesis",
    "Date" : "May 4th, 2016",
    "Still" : "\/aMMyl87dZLVl4Uir6J9J2f9QR1s.jpg"
  },
  {
    "EN" : 21,
    "SN" : 4,
    "Title" : "Monument Point",
    "Date" : "May 11th, 2016",
    "Still" : "\/1RjxyOgWCYNjvrq0N5bRwgAjbgY.jpg"
  },
  {
    "EN" : 22,
    "SN" : 4,
    "Title" : "Lost in the Flood",
    "Date" : "May 18th, 2016",
    "Still" : "\/iPWtuL6qsi9yux3xvOnbHNylrgo.jpg"
  },
  {
    "EN" : 23,
    "SN" : 4,
    "Title" : "Schism",
    "Date" : "May 25th, 2016",
    "Still" : "\/1DKKqCpzr3WvQm09ugSzVuG4hQ3.jpg"
  },
  {
    "EN" : 1,
    "SN" : 3,
    "Title" : "The Calm",
    "Date" : "Oct 8th, 2014",
    "Still" : "\/tW2CBUHvk4eoeyEreCtiv0JYFzr.jpg"
  },
  {
    "EN" : 2,
    "SN" : 3,
    "Title" : "Sara",
    "Date" : "Oct 15th, 2014",
    "Still" : "\/3yGHZjNT4FYVPb9njp52tvalwPN.jpg"
  },
  {
    "EN" : 3,
    "SN" : 3,
    "Title" : "Corto Maltese",
    "Date" : "Oct 22nd, 2014",
    "Still" : "\/1eYJZMcJF3kcmLMIJaW1xPdgyny.jpg"
  },
  {
    "EN" : 4,
    "SN" : 3,
    "Title" : "The Magician",
    "Date" : "Oct 29th, 2014",
    "Still" : "\/wxmNdbnuheA5EEZp9hXQkrytvKR.jpg"
  },
  {
    "EN" : 5,
    "SN" : 3,
    "Title" : "The Secret Origin of Felicity Smoak",
    "Date" : "Nov 5th, 2014",
    "Still" : "\/v8Kch3cTTB5rUqD4Ylk6A1Q1Y3z.jpg"
  },
  {
    "EN" : 6,
    "SN" : 3,
    "Title" : "Guilty",
    "Date" : "Nov 12th, 2014",
    "Still" : "\/begBK9i4d6BeEYrtwzwSQpz62tA.jpg"
  },
  {
    "EN" : 7,
    "SN" : 3,
    "Title" : "Draw Back Your Bow",
    "Date" : "Nov 19th, 2014",
    "Still" : "\/A0WsIK1IP5UZ1scmEex1TYR3Kd7.jpg"
  },
  {
    "EN" : 8,
    "SN" : 3,
    "Title" : "The Brave and the Bold (II)",
    "Date" : "Dec 3rd, 2014",
    "Still" : "\/6xjs0dMUBXjoZQN2Yzg1IBBYVir.jpg"
  },
  {
    "EN" : 9,
    "SN" : 3,
    "Title" : "The Climb",
    "Date" : "Dec 10th, 2014",
    "Still" : "\/tyfBapY2y4iYoTfN2LOGmdghJHJ.jpg"
  },
  {
    "EN" : 10,
    "SN" : 3,
    "Title" : "Left Behind",
    "Date" : "Jan 21st, 2015",
    "Still" : "\/bcVKy6EUtlSHfRbAOKKrm2hlq5k.jpg"
  },
  {
    "EN" : 11,
    "SN" : 3,
    "Title" : "Midnight City",
    "Date" : "Jan 28th, 2015",
    "Still" : "\/vFVXvkOpeFtSR2P8hDzXuiC5FGa.jpg"
  },
  {
    "EN" : 12,
    "SN" : 3,
    "Title" : "Uprising",
    "Date" : "Feb 4th, 2015",
    "Still" : "\/pCiIljplMfI63bWtwWZlszXo8yL.jpg"
  },
  {
    "EN" : 13,
    "SN" : 3,
    "Title" : "Canaries",
    "Date" : "Feb 11th, 2015",
    "Still" : "\/9UTlSRrBFYj1dsmfYFNnIM5JuMe.jpg"
  },
  {
    "EN" : 14,
    "SN" : 3,
    "Title" : "The Return",
    "Date" : "Feb 18th, 2015",
    "Still" : "\/lw4pUj8L4RqmLjEBPjJhBfq7S4X.jpg"
  },
  {
    "EN" : 15,
    "SN" : 3,
    "Title" : "Nanda Parbat",
    "Date" : "Feb 25th, 2015",
    "Still" : "\/zp9zBmwj7i27nIiZauQNCZXFRQ4.jpg"
  },
  {
    "EN" : 16,
    "SN" : 3,
    "Title" : "The Offer",
    "Date" : "Mar 18th, 2015",
    "Still" : "\/flFV4meupmRxU3MejGMM38ZC8Sg.jpg"
  },
  {
    "EN" : 17,
    "SN" : 3,
    "Title" : "Suicidal Tendencies",
    "Date" : "Mar 25th, 2015",
    "Still" : "\/yyaQDWp8iR480tYtmMsIJcy8P7P.jpg"
  },
  {
    "EN" : 18,
    "SN" : 3,
    "Title" : "Public Enemy",
    "Date" : "Apr 1st, 2015",
    "Still" : "\/eDnPFOmyhXxzNNhU95YxPzQPEfE.jpg"
  },
  {
    "EN" : 19,
    "SN" : 3,
    "Title" : "Broken Arrow",
    "Date" : "Apr 15th, 2015",
    "Still" : "\/2EzcgK3cD4MYDvUwrK3qoNAAWrf.jpg"
  },
  {
    "EN" : 20,
    "SN" : 3,
    "Title" : "The Fallen",
    "Date" : "Apr 22nd, 2015",
    "Still" : "\/dVRoLWdIDbGD6bUTu9NPUwW2QCe.jpg"
  },
  {
    "EN" : 21,
    "SN" : 3,
    "Title" : "Al Sah-him",
    "Date" : "Apr 29th, 2015",
    "Still" : "\/xBSwyqMLzsvxZ4yy0SCfyTA3nZe.jpg"
  },
  {
    "EN" : 22,
    "SN" : 3,
    "Title" : "This is Your Sword",
    "Date" : "May 6th, 2015",
    "Still" : "\/303Y2CHEKE50VSYMaqQNQb80oFU.jpg"
  },
  {
    "EN" : 23,
    "SN" : 3,
    "Title" : "My Name Is Oliver Queen",
    "Date" : "May 13th, 2015",
    "Still" : "\/6ov04OKvrVawZdRCWYPpgQm5ftb.jpg"
  },
  {
    "EN" : 1,
    "SN" : 2,
    "Title" : "City of Heroes",
    "Date" : "Oct 9th, 2013",
    "Still" : "\/zqnAl9XvKYgiGpdyxDntJR9Lzn2.jpg"
  },
  {
    "EN" : 2,
    "SN" : 2,
    "Title" : "Identity",
    "Date" : "Oct 16th, 2013",
    "Still" : "\/xGgGU5xeahs0KK5qImAj9B43ZHI.jpg"
  },
  {
    "EN" : 3,
    "SN" : 2,
    "Title" : "Broken Dolls",
    "Date" : "Oct 23rd, 2013",
    "Still" : "\/aFlxt9oeW4oJu6zSKf65rWKZl3.jpg"
  },
  {
    "EN" : 4,
    "SN" : 2,
    "Title" : "Crucible",
    "Date" : "Oct 30th, 2013",
    "Still" : "\/mjtvm4urpEjZXEn9VIkTFuoIy2.jpg"
  },
  {
    "EN" : 5,
    "SN" : 2,
    "Title" : "League of Assassins",
    "Date" : "Nov 6th, 2013",
    "Still" : "\/qkwlm99g3YPQE8o0BIDBn4ADVdE.jpg"
  },
  {
    "EN" : 6,
    "SN" : 2,
    "Title" : "Keep Your Enemies Closer",
    "Date" : "Nov 13th, 2013",
    "Still" : "\/fl2FLNQRJyh2hnSOmcjUl8TWKzF.jpg"
  },
  {
    "EN" : 7,
    "SN" : 2,
    "Title" : "State v. Queen",
    "Date" : "Nov 20th, 2013",
    "Still" : "\/vAVVUh5o4j71ymC0Ldhdg9VvJL1.jpg"
  },
  {
    "EN" : 8,
    "SN" : 2,
    "Title" : "The Scientist",
    "Date" : "Dec 4th, 2013",
    "Still" : "\/rAsQCY3xjURS0WAJqB2CwW7nFm2.jpg"
  },
  {
    "EN" : 9,
    "SN" : 2,
    "Title" : "Three Ghosts",
    "Date" : "Dec 11th, 2013",
    "Still" : "\/ndpVHvr8lHrQWuCOD0IGQrxPDPz.jpg"
  },
  {
    "EN" : 10,
    "SN" : 2,
    "Title" : "Blast Radius",
    "Date" : "Jan 15th, 2014",
    "Still" : "\/eHt9NocxYKVYkfVJ5Cb8jz5EW9A.jpg"
  },
  {
    "EN" : 11,
    "SN" : 2,
    "Title" : "Blind Spot",
    "Date" : "Jan 22nd, 2014",
    "Still" : "\/5ukoueXIv56dMniebT5lFSMmpKH.jpg"
  },
  {
    "EN" : 12,
    "SN" : 2,
    "Title" : "Tremors",
    "Date" : "Jan 29th, 2014",
    "Still" : "\/2XVnWCjNNndVhXvJt5vCGiWeYMD.jpg"
  },
  {
    "EN" : 13,
    "SN" : 2,
    "Title" : "Heir to the Demon",
    "Date" : "Feb 5th, 2014",
    "Still" : "\/rRefpxqXfmFUw7cMQ3PEDYcDnGw.jpg"
  },
  {
    "EN" : 14,
    "SN" : 2,
    "Title" : "Time of Death",
    "Date" : "Feb 26th, 2014",
    "Still" : "\/tZ5a078bJYwcb8Ozv5ROCMnfo9u.jpg"
  },
  {
    "EN" : 15,
    "SN" : 2,
    "Title" : "The Promise",
    "Date" : "Mar 5th, 2014",
    "Still" : "\/670eWrPnICTJ0lbW22vf8P3Wlt7.jpg"
  },
  {
    "EN" : 16,
    "SN" : 2,
    "Title" : "Suicide Squad",
    "Date" : "Mar 19th, 2014",
    "Still" : "\/rSQvxVSfyAjueAq84ubK9uoqv4x.jpg"
  },
  {
    "EN" : 17,
    "SN" : 2,
    "Title" : "Birds of Prey",
    "Date" : "Mar 26th, 2014",
    "Still" : "\/5CUNB89DfsECd8gCsojTZbtfS8F.jpg"
  },
  {
    "EN" : 18,
    "SN" : 2,
    "Title" : "Deathstroke",
    "Date" : "Apr 2nd, 2014",
    "Still" : "\/qgQdgzl4Q3Zf6vIgfcszFpGdfpA.jpg"
  },
  {
    "EN" : 19,
    "SN" : 2,
    "Title" : "The Man Under the Hood",
    "Date" : "Apr 16th, 2014",
    "Still" : "\/fTD11EYeIy7rqfqXI464Q0eb7cE.jpg"
  },
  {
    "EN" : 20,
    "SN" : 2,
    "Title" : "Seeing Red",
    "Date" : "Apr 23rd, 2014",
    "Still" : "\/lMIurwiY5GUlvv4lrFiy0xObmhg.jpg"
  },
  {
    "EN" : 21,
    "SN" : 2,
    "Title" : "City of Blood",
    "Date" : "Apr 30th, 2014",
    "Still" : "\/s4sBTBBJv03rFG9oPp9gpMwsJ3o.jpg"
  },
  {
    "EN" : 22,
    "SN" : 2,
    "Title" : "Streets of Fire",
    "Date" : "May 7th, 2014",
    "Still" : "\/t8zwHTDhFem1Yni78EESR6nJIz1.jpg"
  },
  {
    "EN" : 23,
    "SN" : 2,
    "Title" : "Unthinkable",
    "Date" : "May 14th, 2014",
    "Still" : "\/tIJj4JipZt6pSAGxiAgbBQqemVi.jpg"
  },
  {
    "EN" : 1,
    "SN" : 1,
    "Title" : "Pilot",
    "Date" : "Oct 10th, 2012",
    "Still" : "\/ff5afoT5fCbGfQGjBmF80faqIQU.jpg"
  },
  {
    "EN" : 2,
    "SN" : 1,
    "Title" : "Honor Thy Father",
    "Date" : "Oct 17th, 2012",
    "Still" : "\/vd1muBD34LjjKoHUx0J0Dnx1NGt.jpg"
  },
  {
    "EN" : 3,
    "SN" : 1,
    "Title" : "Lone Gunmen",
    "Date" : "Oct 24th, 2012",
    "Still" : "\/qfhJRnr9xxVPTzEZqfM3qnqzlNg.jpg"
  },
  {
    "EN" : 4,
    "SN" : 1,
    "Title" : "An Innocent Man",
    "Date" : "Oct 31st, 2012",
    "Still" : "\/gf5M5oC7jAuzisQh7uy9XJMzsdO.jpg"
  },
  {
    "EN" : 5,
    "SN" : 1,
    "Title" : "Damaged",
    "Date" : "Nov 7th, 2012",
    "Still" : "\/dy6AyCilp9fbFkaB3iV0jU8o4sd.jpg"
  },
  {
    "EN" : 6,
    "SN" : 1,
    "Title" : "Legacies",
    "Date" : "Nov 14th, 2012",
    "Still" : "\/aMoIdnLnwzeF6amCjuz7mCEpEet.jpg"
  },
  {
    "EN" : 7,
    "SN" : 1,
    "Title" : "Muse of Fire",
    "Date" : "Nov 28th, 2012",
    "Still" : "\/8lJ0vSYeeXm3X57gDzbcLm5b0RD.jpg"
  },
  {
    "EN" : 8,
    "SN" : 1,
    "Title" : "Vendetta",
    "Date" : "Dec 5th, 2012",
    "Still" : "\/i9I8WZJxDksZE9ETqcKD8yWnNP1.jpg"
  },
  {
    "EN" : 9,
    "SN" : 1,
    "Title" : "Year's End",
    "Date" : "Dec 12th, 2012",
    "Still" : "\/ikvn1DwAROee80Pzy4oEfuPaORn.jpg"
  },
  {
    "EN" : 10,
    "SN" : 1,
    "Title" : "Burned",
    "Date" : "Jan 16th, 2013",
    "Still" : "\/5JYPDSgkcS7f1rUIjbuxff48JIb.jpg"
  },
  {
    "EN" : 11,
    "SN" : 1,
    "Title" : "Trust But Verify",
    "Date" : "Jan 23rd, 2013",
    "Still" : "\/6WsgWOZ91lV8oJodxwM3vl5KSxw.jpg"
  },
  {
    "EN" : 12,
    "SN" : 1,
    "Title" : "Vertigo",
    "Date" : "Jan 30th, 2013",
    "Still" : "\/rrq3Pk6XAc3xCX7w46C45F8cH5.jpg"
  },
  {
    "EN" : 13,
    "SN" : 1,
    "Title" : "Betrayal",
    "Date" : "Feb 6th, 2013",
    "Still" : "\/iF9KJ74o7FKmIoKjFO3N6XTWpP0.jpg"
  },
  {
    "EN" : 14,
    "SN" : 1,
    "Title" : "The Odyssey",
    "Date" : "Feb 13th, 2013",
    "Still" : "\/4WErMzAFM4Y0VdLirpArWmRLCmj.jpg"
  },
  {
    "EN" : 15,
    "SN" : 1,
    "Title" : "Dodger",
    "Date" : "Feb 20th, 2013",
    "Still" : "\/zw5UohXDBs9Ko5s2ZxmPL6E7VoB.jpg"
  },
  {
    "EN" : 16,
    "SN" : 1,
    "Title" : "Dead to Rights",
    "Date" : "Feb 27th, 2013",
    "Still" : "\/eQizajQbKrMNOtgTPmuHJBbmR25.jpg"
  },
  {
    "EN" : 17,
    "SN" : 1,
    "Title" : "The Huntress Returns",
    "Date" : "Mar 20th, 2013",
    "Still" : "\/u8brhFmGhsI3DyuAHbw99eduTbE.jpg"
  },
  {
    "EN" : 18,
    "SN" : 1,
    "Title" : "Salvation",
    "Date" : "Mar 27th, 2013",
    "Still" : "\/grBk2rk97jXqsZgpaczrYvnrccW.jpg"
  },
  {
    "EN" : 19,
    "SN" : 1,
    "Title" : "Unfinished Business",
    "Date" : "Apr 3rd, 2013",
    "Still" : "\/y7sWDvX9QgzKaEVjm1TOWrNPPeA.jpg"
  },
  {
    "EN" : 20,
    "SN" : 1,
    "Title" : "Home Invasion",
    "Date" : "Apr 24th, 2013",
    "Still" : "\/1yeRL8ntftdM2Ly8v8B0qx9GP5S.jpg"
  },
  {
    "EN" : 21,
    "SN" : 1,
    "Title" : "The Undertaking",
    "Date" : "May 1st, 2013",
    "Still" : "\/tStBTG7MnTQYfXtX9jlIE45tYR9.jpg"
  },
  {
    "EN" : 22,
    "SN" : 1,
    "Title" : "Darkness on the Edge of Town",
    "Date" : "May 8th, 2013",
    "Still" : "\/oLgqlOxMcILXGvHf7WU1h5KHZT7.jpg"
  },
  {
    "EN" : 23,
    "SN" : 1,
    "Title" : "Sacrifice",
    "Date" : "May 15th, 2013",
    "Still" : "\/bgXrB2ewp9HpjYMQPWHW7qp5rfh.jpg"
  }
]