[
  {
    "Date" : "Nov 24th, 2021",
    "EN" : 1,
    "SN" : 1,
    "Still" : "\/AwCNTaG7VPVwaBRSZkvQUMEfyuZ.jpg",
    "Title" : "Never Meet Your Heroes"
  },
  {
    "Date" : "Nov 24th, 2021",
    "EN" : 2,
    "SN" : 1,
    "Still" : "\/v6DjX5jATXUpkILMFMEOR61PWr5.jpg",
    "Title" : "Hide and Seek"
  },
  {
    "Date" : "Dec 1st, 2021",
    "EN" : 3,
    "SN" : 1,
    "Still" : "\/4JIxm0YFv0d8nMEwmMBrOOs2H0k.jpg",
    "Title" : "Echoes"
  },
  {
    "Date" : "Dec 8th, 2021",
    "EN" : 4,
    "SN" : 1,
    "Still" : "\/3K3CPASP9NhbxPwkSvCskRpmzTL.jpg",
    "Title" : "Partners, Am I Right?"
  },
  {
    "Date" : "Dec 15th, 2021",
    "EN" : 5,
    "SN" : 1,
    "Still" : "\/oaDRxEaBGVFqYyc4ycbyLRstZ1F.jpg",
    "Title" : "Ronin"
  },
  {
    "Date" : "Dec 22nd, 2021",
    "EN" : 6,
    "SN" : 1,
    "Still" : "\/4nZb3KEYvv7OmNLET33dtAjAvgB.jpg",
    "Title" : "So This Is Christmas?"
  }
]