{"TMDBID": 277217, "IMDBID": "tt3440298", "Poster": "65DkgHPSLVjgr6IYkpY9Aqqqid5.jpg", "MediaType": 1, "Tagline": "They're not bad. They're just born that way.", "Summary": "A present-day idyllic kingdom where the benevolent teenage son of King Adam and Queen Belle offers a chance of redemption for the troublemaking offspring of Disney's classic villains: Cruella De Vil (Carlos), Maleficent (Mal), the Evil Queen (Evie) and Jafar (Jay).", "Tile1Title": "Runtime", "Tile2Title": "Status", "Tile1SubTitle": "112 Minutes", "Tile2SubTitle": "Released"}