{"TMDBID": 911916, "IMDBID": "tt16360004", "Poster": "5cAuJOfd5tuuFBz2yQmBCtVBaj0.jpg", "MediaType": 1, "Tagline": "", "Summary": "Taking place right after the events of Spider-Man: Across the Spider-Verse, Gwen Stacy leads the newly reformed Spider-Gang in a race against the Spider-Society, led by Miguel O'Hara, to find Miles Morales, who is trapped in the home dimension of the spider that bit him, along with an alternate version of himself as the Prowler, while the Spot begins his deadly attack in his dimension with far-reaching multiversal consequences.", "Tile1Title": "Runtime", "Tile2Title": "Status", "Tile1SubTitle": "0 Minutes", "Tile2SubTitle": "In Production"}